wyzeapi/__init__.py
wyzeapi/client.py
wyzeapi/constants.py
wyzeapi/devices/__init__.py
wyzeapi/devices/base.py
wyzeapi/devices/base_networked_device.py
wyzeapi/devices/base_sensor.py
wyzeapi/devices/bulb.py
wyzeapi/devices/contact_sensor.py
wyzeapi/devices/lock.py
wyzeapi/devices/motion_sensor.py
wyzeapi/devices/switch.py
wyzeapi/interfaces/ISwitchable.py
wyzeapi/interfaces/IUpdatable.py
wyzeapi/interfaces/__init__.py
wyzeapi_JoshMulliken-0.0.1.dist-info/LICENSE
wyzeapi_JoshMulliken-0.0.1.dist-info/METADATA
wyzeapi_JoshMulliken-0.0.1.dist-info/WHEEL
wyzeapi_JoshMulliken-0.0.1.dist-info/top_level.txt
wyzeapi_JoshMulliken-0.0.1.dist-info/RECORD
